gee_subset/__init__.py
gee_subset/gee_subset.py
gee_subset-1.1.2.dist-info/LICENSE
gee_subset-1.1.2.dist-info/METADATA
gee_subset-1.1.2.dist-info/WHEEL
gee_subset-1.1.2.dist-info/top_level.txt
gee_subset-1.1.2.dist-info/RECORD
