Metadata-Version: 2.1
Name: gee-subset
Version: 1.1.2
Summary: Subset Google Earth Engine data
Home-page: https://github.com/bluegreen-labs/gee_subset
Author: Koen Hufkens
Author-email: koen.hufkens@gmail.com
License: AGPL-3
Download-URL: https://github.com/bluegreen-labs/gee_subset/archive/1.1.2.tar.gz
Project-URL: Bug Tracker, https://github.com/pypa/sampleproject/issues
Keywords: remote sensing,api,subsets
Platform: UNKNOWN
Classifier: Development Status :: 5 - Production/Stable
Classifier: Intended Audience :: Science/Research
Classifier: Topic :: Scientific/Engineering :: Information Analysis
Classifier: License :: OSI Approved :: GNU Affero General Public License v3
Classifier: Programming Language :: Python :: 3.6
Classifier: Programming Language :: Python :: 2.7
Classifier: Programming Language :: Python :: 2.6
Requires-Python: >=3.6
License-File: LICENSE
